{
  "_format": "hh-sol-cache-2",
  "files": {
    "C:\\Users\\emi\\Desktop\\blockchains\\kortanablockchain-devhub\\kortana-aether\\contracts\\contracts\\EscrowManager.sol": {
      "lastModificationDate": 1770535373579,
      "contentHash": "0386a8c18377abd28ebfc35e1991fc6f",
      "sourceName": "contracts/EscrowManager.sol",
      "solcConfig": {
        "version": "0.8.20",
        "settings": {
          "evmVersion": "paris",
          "optimizer": {
            "enabled": true,
            "runs": 200
          },
          "outputSelection": {
            "*": {
              "*": [
                "abi",
                "evm.bytecode",
                "evm.deployedBytecode",
                "evm.methodIdentifiers",
                "metadata"
              ],
              "": [
                "ast"
              ]
            }
          }
        }
      },
      "imports": [
        "@openzeppelin/contracts/access/Ownable.sol",
        "@openzeppelin/contracts/token/ERC20/IERC20.sol",
        "@openzeppelin/contracts/utils/ReentrancyGuard.sol"
      ],
      "versionPragmas": [
        "^0.8.20"
      ],
      "artifacts": [
        "EscrowManager"
      ]
    },
    "C:\\Users\\emi\\Desktop\\blockchains\\kortanablockchain-devhub\\kortana-aether\\contracts\\node_modules\\@openzeppelin\\contracts\\utils\\ReentrancyGuard.sol": {
      "lastModificationDate": 1770490616389,
      "contentHash": "190613e556d509d9e9a0ea43dc5d891d",
      "sourceName": "@openzeppelin/contracts/utils/ReentrancyGuard.sol",
      "solcConfig": {
        "version": "0.8.20",
        "settings": {
          "evmVersion": "paris",
          "optimizer": {
            "enabled": true,
            "runs": 200
          },
          "outputSelection": {
            "*": {
              "*": [
                "abi",
                "evm.bytecode",
                "evm.deployedBytecode",
                "evm.methodIdentifiers",
                "metadata"
              ],
              "": [
                "ast"
              ]
            }
          }
        }
      },
      "imports": [],
      "versionPragmas": [
        "^0.8.20"
      ],
      "artifacts": [
        "ReentrancyGuard"
      ]
    },
    "C:\\Users\\emi\\Desktop\\blockchains\\kortanablockchain-devhub\\kortana-aether\\contracts\\node_modules\\@openzeppelin\\contracts\\access\\Ownable.sol": {
      "lastModificationDate": 1770490616331,
      "contentHash": "d3c790edc9ccf808a17c5a6cd13614fd",
      "sourceName": "@openzeppelin/contracts/access/Ownable.sol",
      "solcConfig": {
        "version": "0.8.20",
        "settings": {
          "evmVersion": "paris",
          "optimizer": {
            "enabled": true,
            "runs": 200
          },
          "outputSelection": {
            "*": {
              "*": [
                "abi",
                "evm.bytecode",
                "evm.deployedBytecode",
                "evm.methodIdentifiers",
                "metadata"
              ],
              "": [
                "ast"
              ]
            }
          }
        }
      },
      "imports": [
        "../utils/Context.sol"
      ],
      "versionPragmas": [
        "^0.8.20"
      ],
      "artifacts": [
        "Ownable"
      ]
    },
    "C:\\Users\\emi\\Desktop\\blockchains\\kortanablockchain-devhub\\kortana-aether\\contracts\\node_modules\\@openzeppelin\\contracts\\token\\ERC20\\IERC20.sol": {
      "lastModificationDate": 1770490616026,
      "contentHash": "9261adf6457863de3e9892f51317ec89",
      "sourceName": "@openzeppelin/contracts/token/ERC20/IERC20.sol",
      "solcConfig": {
        "version": "0.8.20",
        "settings": {
          "evmVersion": "paris",
          "optimizer": {
            "enabled": true,
            "runs": 200
          },
          "outputSelection": {
            "*": {
              "*": [
                "abi",
                "evm.bytecode",
                "evm.deployedBytecode",
                "evm.methodIdentifiers",
                "metadata"
              ],
              "": [
                "ast"
              ]
            }
          }
        }
      },
      "imports": [],
      "versionPragmas": [
        ">=0.4.16"
      ],
      "artifacts": [
        "IERC20"
      ]
    },
    "C:\\Users\\emi\\Desktop\\blockchains\\kortanablockchain-devhub\\kortana-aether\\contracts\\node_modules\\@openzeppelin\\contracts\\utils\\Context.sol": {
      "lastModificationDate": 1770490614851,
      "contentHash": "67bfbc07588eb8683b3fd8f6f909563e",
      "sourceName": "@openzeppelin/contracts/utils/Context.sol",
      "solcConfig": {
        "version": "0.8.20",
        "settings": {
          "evmVersion": "paris",
          "optimizer": {
            "enabled": true,
            "runs": 200
          },
          "outputSelection": {
            "*": {
              "*": [
                "abi",
                "evm.bytecode",
                "evm.deployedBytecode",
                "evm.methodIdentifiers",
                "metadata"
              ],
              "": [
                "ast"
              ]
            }
          }
        }
      },
      "imports": [],
      "versionPragmas": [
        "^0.8.20"
      ],
      "artifacts": [
        "Context"
      ]
    },
    "C:\\Users\\emi\\Desktop\\blockchains\\kortanablockchain-devhub\\kortana-aether\\contracts\\node_modules\\@openzeppelin\\contracts\\token\\ERC20\\extensions\\IERC20Metadata.sol": {
      "lastModificationDate": 1770490616040,
      "contentHash": "513778b30d2750f5d2b9b19bbcf748a5",
      "sourceName": "@openzeppelin/contracts/token/ERC20/extensions/IERC20Metadata.sol",
      "solcConfig": {
        "version": "0.8.20",
        "settings": {
          "evmVersion": "paris",
          "optimizer": {
            "enabled": true,
            "runs": 200
          },
          "outputSelection": {
            "*": {
              "*": [
                "abi",
                "evm.bytecode",
                "evm.deployedBytecode",
                "evm.methodIdentifiers",
                "metadata"
              ],
              "": [
                "ast"
              ]
            }
          }
        }
      },
      "imports": [
        "../IERC20.sol"
      ],
      "versionPragmas": [
        ">=0.6.2"
      ],
      "artifacts": [
        "IERC20Metadata"
      ]
    },
    "C:\\Users\\emi\\Desktop\\blockchains\\kortanablockchain-devhub\\kortana-aether\\contracts\\node_modules\\@openzeppelin\\contracts\\token\\ERC20\\ERC20.sol": {
      "lastModificationDate": 1770490615318,
      "contentHash": "59dfce11284f2636db261df9b6a18f81",
      "sourceName": "@openzeppelin/contracts/token/ERC20/ERC20.sol",
      "solcConfig": {
        "version": "0.8.20",
        "settings": {
          "evmVersion": "paris",
          "optimizer": {
            "enabled": true,
            "runs": 200
          },
          "outputSelection": {
            "*": {
              "*": [
                "abi",
                "evm.bytecode",
                "evm.deployedBytecode",
                "evm.methodIdentifiers",
                "metadata"
              ],
              "": [
                "ast"
              ]
            }
          }
        }
      },
      "imports": [
        "./IERC20.sol",
        "./extensions/IERC20Metadata.sol",
        "../../utils/Context.sol",
        "../../interfaces/draft-IERC6093.sol"
      ],
      "versionPragmas": [
        "^0.8.20"
      ],
      "artifacts": [
        "ERC20"
      ]
    },
    "C:\\Users\\emi\\Desktop\\blockchains\\kortanablockchain-devhub\\kortana-aether\\contracts\\node_modules\\@openzeppelin\\contracts\\interfaces\\draft-IERC6093.sol": {
      "lastModificationDate": 1770490615079,
      "contentHash": "5041977bbe908de2e6ed0270447f79ad",
      "sourceName": "@openzeppelin/contracts/interfaces/draft-IERC6093.sol",
      "solcConfig": {
        "version": "0.8.20",
        "settings": {
          "evmVersion": "paris",
          "optimizer": {
            "enabled": true,
            "runs": 200
          },
          "outputSelection": {
            "*": {
              "*": [
                "abi",
                "evm.bytecode",
                "evm.deployedBytecode",
                "evm.methodIdentifiers",
                "metadata"
              ],
              "": [
                "ast"
              ]
            }
          }
        }
      },
      "imports": [],
      "versionPragmas": [
        ">=0.8.4"
      ],
      "artifacts": [
        "IERC1155Errors",
        "IERC20Errors",
        "IERC721Errors"
      ]
    },
    "C:\\Users\\emi\\Desktop\\blockchains\\kortanablockchain-devhub\\kortana-aether\\contracts\\node_modules\\@openzeppelin\\contracts\\token\\ERC20\\extensions\\ERC20Pausable.sol": {
      "lastModificationDate": 1770490615362,
      "contentHash": "a3ce035689a60e32921347c16a3fb786",
      "sourceName": "@openzeppelin/contracts/token/ERC20/extensions/ERC20Pausable.sol",
      "solcConfig": {
        "version": "0.8.20",
        "settings": {
          "evmVersion": "paris",
          "optimizer": {
            "enabled": true,
            "runs": 200
          },
          "outputSelection": {
            "*": {
              "*": [
                "abi",
                "evm.bytecode",
                "evm.deployedBytecode",
                "evm.methodIdentifiers",
                "metadata"
              ],
              "": [
                "ast"
              ]
            }
          }
        }
      },
      "imports": [
        "../ERC20.sol",
        "../../../utils/Pausable.sol"
      ],
      "versionPragmas": [
        "^0.8.20"
      ],
      "artifacts": [
        "ERC20Pausable"
      ]
    },
    "C:\\Users\\emi\\Desktop\\blockchains\\kortanablockchain-devhub\\kortana-aether\\contracts\\node_modules\\@openzeppelin\\contracts\\utils\\Pausable.sol": {
      "lastModificationDate": 1770490616367,
      "contentHash": "0d47b53e10b1985efbb396f937626279",
      "sourceName": "@openzeppelin/contracts/utils/Pausable.sol",
      "solcConfig": {
        "version": "0.8.20",
        "settings": {
          "evmVersion": "paris",
          "optimizer": {
            "enabled": true,
            "runs": 200
          },
          "outputSelection": {
            "*": {
              "*": [
                "abi",
                "evm.bytecode",
                "evm.deployedBytecode",
                "evm.methodIdentifiers",
                "metadata"
              ],
              "": [
                "ast"
              ]
            }
          }
        }
      },
      "imports": [
        "../utils/Context.sol"
      ],
      "versionPragmas": [
        "^0.8.20"
      ],
      "artifacts": [
        "Pausable"
      ]
    },
    "C:\\Users\\emi\\Desktop\\blockchains\\kortanablockchain-devhub\\kortana-aether\\contracts\\contracts\\RentalDistribution.sol": {
      "lastModificationDate": 1770490809818,
      "contentHash": "f0b217977a3f43951a28a49afd93513c",
      "sourceName": "contracts/RentalDistribution.sol",
      "solcConfig": {
        "version": "0.8.20",
        "settings": {
          "evmVersion": "paris",
          "optimizer": {
            "enabled": true,
            "runs": 200
          },
          "outputSelection": {
            "*": {
              "*": [
                "abi",
                "evm.bytecode",
                "evm.deployedBytecode",
                "evm.methodIdentifiers",
                "metadata"
              ],
              "": [
                "ast"
              ]
            }
          }
        }
      },
      "imports": [
        "@openzeppelin/contracts/access/Ownable.sol",
        "@openzeppelin/contracts/token/ERC20/IERC20.sol",
        "@openzeppelin/contracts/utils/ReentrancyGuard.sol"
      ],
      "versionPragmas": [
        "^0.8.20"
      ],
      "artifacts": [
        "RentalDistribution"
      ]
    },
    "C:\\Users\\emi\\Desktop\\blockchains\\kortanablockchain-devhub\\kortana-aether\\contracts\\contracts\\PropertyToken.sol": {
      "lastModificationDate": 1770535421593,
      "contentHash": "1c5b71fdec862daba2669760651301ea",
      "sourceName": "contracts/PropertyToken.sol",
      "solcConfig": {
        "version": "0.8.20",
        "settings": {
          "evmVersion": "paris",
          "optimizer": {
            "enabled": true,
            "runs": 200
          },
          "outputSelection": {
            "*": {
              "*": [
                "abi",
                "evm.bytecode",
                "evm.deployedBytecode",
                "evm.methodIdentifiers",
                "metadata"
              ],
              "": [
                "ast"
              ]
            }
          }
        }
      },
      "imports": [
        "@openzeppelin/contracts/token/ERC20/ERC20.sol",
        "@openzeppelin/contracts/token/ERC20/extensions/ERC20Pausable.sol",
        "@openzeppelin/contracts/access/Ownable.sol"
      ],
      "versionPragmas": [
        "^0.8.20"
      ],
      "artifacts": [
        "PropertyToken"
      ]
    },
    "C:\\Users\\emi\\Desktop\\blockchains\\kortanablockchain-devhub\\kortana-aether\\contracts\\contracts\\PropertyRegistry.sol": {
      "lastModificationDate": 1770535380643,
      "contentHash": "cb2374170b62d43b26e29f2eeea1a66b",
      "sourceName": "contracts/PropertyRegistry.sol",
      "solcConfig": {
        "version": "0.8.20",
        "settings": {
          "evmVersion": "paris",
          "optimizer": {
            "enabled": true,
            "runs": 200
          },
          "outputSelection": {
            "*": {
              "*": [
                "abi",
                "evm.bytecode",
                "evm.deployedBytecode",
                "evm.methodIdentifiers",
                "metadata"
              ],
              "": [
                "ast"
              ]
            }
          }
        }
      },
      "imports": [
        "@openzeppelin/contracts/access/Ownable.sol"
      ],
      "versionPragmas": [
        "^0.8.20"
      ],
      "artifacts": [
        "PropertyRegistry"
      ]
    },
    "C:\\Users\\emi\\Desktop\\blockchains\\kortanablockchain-devhub\\kortana-aether\\contracts\\contracts\\SimpleToken.sol": {
      "lastModificationDate": 1770535396546,
      "contentHash": "4e0e044cfec31e692d7d0c4d1bd944ce",
      "sourceName": "contracts/SimpleToken.sol",
      "solcConfig": {
        "version": "0.8.20",
        "settings": {
          "evmVersion": "paris",
          "optimizer": {
            "enabled": true,
            "runs": 200
          },
          "outputSelection": {
            "*": {
              "*": [
                "abi",
                "evm.bytecode",
                "evm.deployedBytecode",
                "evm.methodIdentifiers",
                "metadata"
              ],
              "": [
                "ast"
              ]
            }
          }
        }
      },
      "imports": [],
      "versionPragmas": [
        "^0.8.20"
      ],
      "artifacts": [
        "SimpleToken"
      ]
    }
  }
}
